SADemo/API_longchuang.py
SADemo/HelloWorld.py
SADemo/SA_API.py
SADemo/__init__.py
SADemo/manifast.py
SADemo/person.py
SADemo/test4.py
mymain/__init__.py
mymain/demog.py
yuejzDemo-0.0.8.dist-info/LICENSE
yuejzDemo-0.0.8.dist-info/METADATA
yuejzDemo-0.0.8.dist-info/WHEEL
yuejzDemo-0.0.8.dist-info/top_level.txt
yuejzDemo-0.0.8.dist-info/RECORD
