Metadata-Version: 2.1
Name: yuejzDemo
Version: 0.0.8
Summary: This is my demo
Home-page: https://github.com/hylinux1024/niubiproject
Author: YueJZdsa
Author-email: yuejianzhong@sensorsdata.cn
License: UNKNOWN
Platform: UNKNOWN
